topsis_aditya/__init__.py
topsis_aditya/topsis.py
topsis_aditya_102303526-1.0.0.dist-info/licenses/LICENSE
topsis_aditya_102303526-1.0.0.dist-info/METADATA
topsis_aditya_102303526-1.0.0.dist-info/WHEEL
topsis_aditya_102303526-1.0.0.dist-info/entry_points.txt
topsis_aditya_102303526-1.0.0.dist-info/top_level.txt
topsis_aditya_102303526-1.0.0.dist-info/RECORD
