Metadata-Version: 2.4
Name: Topsis-Aditya-102303526
Version: 1.0.0
Summary: TOPSIS implementation as a Python package
Author: Aditya
License-File: LICENSE
Requires-Dist: pandas
Requires-Dist: numpy
Requires-Dist: openpyxl
Dynamic: author
Dynamic: description
Dynamic: description-content-type
Dynamic: license-file
Dynamic: requires-dist
Dynamic: summary
